embeam/__init__.py
embeam/coherent.py
embeam/constants.py
embeam/gun.py
embeam/lens.py
embeam/version.py
embeam/stem/__init__.py
embeam/stem/probe/__init__.py
embeam/stem/probe/kspace.py
embeam/stem/probe/resolution.py
embeam/stem/probe/discretized/__init__.py
embeam/stem/probe/discretized/kspace.py
embeam/stem/probe/discretized/periodic/__init__.py
embeam/stem/probe/discretized/periodic/rspace.py
embeam/stem/probe/discretized/symmetric/__init__.py
embeam/stem/probe/discretized/symmetric/rspace.py
embeam/stem/probe/symmetric/__init__.py
embeam/stem/probe/symmetric/rspace.py
embeam-0.0.5.dist-info/licenses/LICENSE
embeam-0.0.5.dist-info/METADATA
embeam-0.0.5.dist-info/WHEEL
embeam-0.0.5.dist-info/top_level.txt
embeam-0.0.5.dist-info/RECORD
